ai_minecraft_skin/__init__.py
ai_minecraft_skin-1766732.2.123.dist-info/licenses/LICENSE
ai_minecraft_skin-1766732.2.123.dist-info/METADATA
ai_minecraft_skin-1766732.2.123.dist-info/WHEEL
ai_minecraft_skin-1766732.2.123.dist-info/top_level.txt
ai_minecraft_skin-1766732.2.123.dist-info/RECORD
