Metadata-Version: 2.4
Name: ai-minecraft-skin
Version: 1766732.2.123
Summary: High-quality integration for https://supermaker.ai/image/ai-minecraft-skin/
Home-page: https://supermaker.ai/image/ai-minecraft-skin/
Author: SuperMaker
Classifier: Programming Language :: Python :: 3
Classifier: License :: OSI Approved :: MIT License
Requires-Python: >=3.6
License-File: LICENSE
Dynamic: author
Dynamic: classifier
Dynamic: description
Dynamic: description-content-type
Dynamic: home-page
Dynamic: license-file
Dynamic: requires-python
Dynamic: summary
